[
  {"id": "U001", "name": "Alice Johnson", "email": "alice.johnson@example.com", "region": "US", "signup_date": "2023-10-12"},
  {"id": "U002", "name": "Bob Smith", "email": "bob.smith@example.com", "region": "EU", "signup_date": "2023-11-05"},
  {"id": "U003", "name": "Charlie Kim", "email": "charlie.kim@example.com", "region": "APAC", "signup_date": "2023-08-19"},
  {"id": "U004", "name": "Diana Lopez", "email": "diana.lopez@example.com", "region": "US", "signup_date": "2023-07-24"},
  {"id": "U005", "name": "Ethan Williams", "email": "ethan.williams@example.com", "region": "EU", "signup_date": "2023-06-30"},
  {"id": "U006", "name": "Fiona Patel", "email": "fiona.patel@example.com", "region": "US", "signup_date": "2023-09-15"},
  {"id": "U007", "name": "George Chen", "email": "george.chen@example.com", "region": "APAC", "signup_date": "2023-10-01"},
  {"id": "U008", "name": "Hannah Brown", "email": "hannah.brown@example.com", "region": "EU", "signup_date": "2023-05-27"},
  {"id": "U009", "name": "Ian Davis", "email": "ian.davis@example.com", "region": "US", "signup_date": "2023-03-22"},
  {"id": "U010", "name": "Julia Martin", "email": "julia.martin@example.com", "region": "EU", "signup_date": "2023-02-18"},
  {"id": "U011", "name": "Kevin Park", "email": "kevin.park@example.com", "region": "APAC", "signup_date": "2023-07-05"},
  {"id": "U012", "name": "Laura Gonzalez", "email": "laura.gonzalez@example.com", "region": "US", "signup_date": "2023-01-20"},
  {"id": "U013", "name": "Michael Scott", "email": "michael.scott@example.com", "region": "EU", "signup_date": "2023-03-11"},
  {"id": "U014", "name": "Nina Harris", "email": "nina.harris@example.com", "region": "US", "signup_date": "2023-05-15"},
  {"id": "U015", "name": "Oscar Reed", "email": "oscar.reed@example.com", "region": "EU", "signup_date": "2023-04-10"},
  {"id": "U016", "name": "Paula King", "email": "paula.king@example.com", "region": "APAC", "signup_date": "2023-08-01"},
  {"id": "U017", "name": "Quentin Evans", "email": "quentin.evans@example.com", "region": "US", "signup_date": "2023-06-02"},
  {"id": "U018", "name": "Rita Carter", "email": "rita.carter@example.com", "region": "EU", "signup_date": "2023-09-19"},
  {"id": "U019", "name": "Samir Khan", "email": "samir.khan@example.com", "region": "APAC", "signup_date": "2023-10-09"},
  {"id": "U020", "name": "Tina Baker", "email": "tina.baker@example.com", "region": "US", "signup_date": "2023-11-02"},
  {"id": "U021", "name": "Uma Larson", "email": "uma.larson@example.com", "region": "EU", "signup_date": "2023-12-01"},
  {"id": "U022", "name": "Victor Adams", "email": "victor.adams@example.com", "region": "US", "signup_date": "2023-07-21"},
  {"id": "U023", "name": "Wendy Nguyen", "email": "wendy.nguyen@example.com", "region": "APAC", "signup_date": "2023-09-10"},
  {"id": "U024", "name": "Xavier Bell", "email": "xavier.bell@example.com", "region": "EU", "signup_date": "2023-08-15"},
  {"id": "U025", "name": "Yara Cooper", "email": "yara.cooper@example.com", "region": "US", "signup_date": "2023-05-29"},
  {"id": "U026", "name": "Zane Patel", "email": "zane.patel@example.com", "region": "APAC", "signup_date": "2023-10-13"},
  {"id": "U027", "name": "Aaron Carter", "email": "aaron.carter@example.com", "region": "EU", "signup_date": "2023-03-30"},
  {"id": "U028", "name": "Bella Thomas", "email": "bella.thomas@example.com", "region": "US", "signup_date": "2023-04-18"},
  {"id": "U029", "name": "Caleb Green", "email": "caleb.green@example.com", "region": "EU", "signup_date": "2023-05-12"},
  {"id": "U030", "name": "Daisy White", "email": "daisy.white@example.com", "region": "US", "signup_date": "2023-07-08"},
  {"id": "U031", "name": "Eli Turner", "email": "eli.turner@example.com", "region": "APAC", "signup_date": "2023-06-26"},
  {"id": "U032", "name": "Farah Ali", "email": "farah.ali@example.com", "region": "US", "signup_date": "2023-02-22"},
  {"id": "U033", "name": "Gavin Ortiz", "email": "gavin.ortiz@example.com", "region": "EU", "signup_date": "2023-08-14"},
  {"id": "U034", "name": "Hailey Stone", "email": "hailey.stone@example.com", "region": "APAC", "signup_date": "2023-09-05"},
  {"id": "U035", "name": "Isaac Murphy", "email": "isaac.murphy@example.com", "region": "US", "signup_date": "2023-03-03"},
  {"id": "U036", "name": "Jenna Allen", "email": "jenna.allen@example.com", "region": "EU", "signup_date": "2023-05-01"},
  {"id": "U037", "name": "Kyle Reed", "email": "kyle.reed@example.com", "region": "US", "signup_date": "2023-06-11"},
  {"id": "U038", "name": "Lara Brooks", "email": "lara.brooks@example.com", "region": "APAC", "signup_date": "2023-07-19"},
  {"id": "U039", "name": "Mason Rivera", "email": "mason.rivera@example.com", "region": "EU", "signup_date": "2023-04-23"},
  {"id": "U040", "name": "Nora Hayes", "email": "nora.hayes@example.com", "region": "US", "signup_date": "2023-03-10"},
  {"id": "U041", "name": "Omar Ali", "email": "omar.ali@example.com", "region": "APAC", "signup_date": "2023-05-05"},
  {"id": "U042", "name": "Penny Ward", "email": "penny.ward@example.com", "region": "EU", "signup_date": "2023-08-12"},
  {"id": "U043", "name": "Quinn Ross", "email": "quinn.ross@example.com", "region": "US", "signup_date": "2023-10-22"},
  {"id": "U044", "name": "Rosa Patel", "email": "rosa.patel@example.com", "region": "APAC", "signup_date": "2023-09-29"},
  {"id": "U045", "name": "Sean Cooper", "email": "sean.cooper@example.com", "region": "US", "signup_date": "2023-07-31"},
  {"id": "U046", "name": "Tara Nguyen", "email": "tara.nguyen@example.com", "region": "EU", "signup_date": "2023-06-20"},
  {"id": "U047", "name": "Umar Singh", "email": "umar.singh@example.com", "region": "APAC", "signup_date": "2023-11-08"},
  {"id": "U048", "name": "Vera Hall", "email": "vera.hall@example.com", "region": "US", "signup_date": "2023-05-09"},
  {"id": "U049", "name": "Will Reed", "email": "will.reed@example.com", "region": "EU", "signup_date": "2023-07-17"},
  {"id": "U050", "name": "Zoe Kim", "email": "zoe.kim@example.com", "region": "APAC", "signup_date": "2023-09-01"}
]
